Workbook

Sheet 📋 Guide
A1: AI TOOL COMPARISON MATRIX
A2: AI-Powered Process Automation for Business Operations | Participant Tool
A4: HOW TO USE THIS TOOL
A5: STEP 1 | B5: Go to '⚖️ Scoring Matrix'. Review each evaluation criterion and its weighting.
A6: STEP 2 | B6: In the BLUE cells, enter your company's context (use case, budget, team size, etc.).
A7: STEP 3 | B7: Rate each tool from 1–5 for each criterion. Ratings are your professional judgement.
A8: STEP 4 | B8: Weighted scores are calculated automatically. The highest score = recommended tool.
A9: STEP 5 | B9: Visit '📊 Tool Profiles' to read a detailed profile of each platform.
A10: STEP 6 | B10: Review your final recommendation in '🏆 My Recommendation' and print to share.
A12: EVALUATION CRITERIA EXPLAINED
A13: Ease of Use (20%) | D13: How quickly can non-technical staff learn and use the tool independently?
A14: Integration Fit (25%) | D14: How well does the tool connect to your existing systems (M365, ERP, CRM, databases)?
A15: AI / ML Capability (20%) | D15: Depth of AI features: NLP, document understanding, predictions, generative AI.
A16: Security & Compliance (15%) | D16: Data encryption, access control, PDPA/GDPR readiness, audit logging.
A17: Cost Effectiveness (10%) | D17: Total cost of ownership relative to expected value delivered.
A18: Vendor Support (10%) | D18: Quality of local support, documentation, community, and training resources.
A20: Fakhrul Syahmi | Data Consultant & Certified Trainer | mufasyahcons@gmail.com | © 2026

Sheet ⚖️ Scoring Matrix
A1: ⚖️ AI TOOL SCORING MATRIX — Score Each Tool 1–5 Per Criterion
A2: Rate each tool from 1 (Poor) to 5 (Excellent) for each criterion below. Weighted score = rating × weight.
A4: YOUR COMPANY CONTEXT (Fill in these details first)
B5: Company / Organisation Name | F5: Primary Use Case / Process | J5: Current Main System
A7: Criterion | B7: Weight | C7: Rating Guide | D7: Power Automate | E7: UiPath | F7: Auto Anywhere | G7: MS Copilot | H7: Zapier | I7: Make.com | J7: Best Tool
A8: Ease of Use | B8: 0.2 | C8: 1=Requires developers 5=Fully no-code | J8: =IFERROR(IF(MAX(D8,E8,F8,G8,H8,I8)=0,"Enter ratings",ifs(D8=MAX(D8,E8,F8,G8,H8,I8),"Power Automate",E8=MAX(D8,E8,F8,G8,H8,I8),"UiPath",F8=MAX(D8,E8,F8,G8,H8,I8),"Auto Anywhere",G8=MAX(D8,E8,F8,G8,H8,I8),"MS Copilot",H8=MAX(D8,E8,F8,G8,H8,I8),"Zapier",I8=MAX(D8,E8,F8,G8,H8,I8),"Make.com")),"Enter ratings") -> Enter ratings
A9: Integration Fit | B9: 0.25 | C9: 1=No connectors 5=Native to your systems | J9: =IFERROR(IF(MAX(D9,E9,F9,G9,H9,I9)=0,"Enter ratings",ifs(D9=MAX(D9,E9,F9,G9,H9,I9),"Power Automate",E9=MAX(D9,E9,F9,G9,H9,I9),"UiPath",F9=MAX(D9,E9,F9,G9,H9,I9),"Auto Anywhere",G9=MAX(D9,E9,F9,G9,H9,I9),"MS Copilot",H9=MAX(D9,E9,F9,G9,H9,I9),"Zapier",I9=MAX(D9,E9,F9,G9,H9,I9),"Make.com")),"Enter ratings") -> Enter ratings
A10: AI / ML Capability | B10: 0.2 | C10: 1=Basic automation only 5=Full AI/NLP/GenAI | J10: =IFERROR(IF(MAX(D10,E10,F10,G10,H10,I10)=0,"Enter ratings",ifs(D10=MAX(D10,E10,F10,G10,H10,I10),"Power Automate",E10=MAX(D10,E10,F10,G10,H10,I10),"UiPath",F10=MAX(D10,E10,F10,G10,H10,I10),"Auto Anywhere",G10=MAX(D10,E10,F10,G10,H10,I10),"MS Copilot",H10=MAX(D10,E10,F10,G10,H10,I10),"Zapier",I10=MAX(D10,E10,F10,G10,H10,I10),"Make.com")),"Enter ratings") -> Enter ratings
A11: Security & Compliance | B11: 0.15 | C11: 1=No compliance certs 5=SOC2,GDPR,PDPA ready | J11: =IFERROR(IF(MAX(D11,E11,F11,G11,H11,I11)=0,"Enter ratings",ifs(D11=MAX(D11,E11,F11,G11,H11,I11),"Power Automate",E11=MAX(D11,E11,F11,G11,H11,I11),"UiPath",F11=MAX(D11,E11,F11,G11,H11,I11),"Auto Anywhere",G11=MAX(D11,E11,F11,G11,H11,I11),"MS Copilot",H11=MAX(D11,E11,F11,G11,H11,I11),"Zapier",I11=MAX(D11,E11,F11,G11,H11,I11),"Make.com")),"Enter ratings") -> Enter ratings
A12: Cost Effectiveness | B12: 0.1 | C12: 1=Very expensive 5=Best value for money | J12: =IFERROR(IF(MAX(D12,E12,F12,G12,H12,I12)=0,"Enter ratings",ifs(D12=MAX(D12,E12,F12,G12,H12,I12),"Power Automate",E12=MAX(D12,E12,F12,G12,H12,I12),"UiPath",F12=MAX(D12,E12,F12,G12,H12,I12),"Auto Anywhere",G12=MAX(D12,E12,F12,G12,H12,I12),"MS Copilot",H12=MAX(D12,E12,F12,G12,H12,I12),"Zapier",I12=MAX(D12,E12,F12,G12,H12,I12),"Make.com")),"Enter ratings") -> Enter ratings
A13: Vendor Support | B13: 0.1 | C13: 1=Community only 5=24/7 local support | J13: =IFERROR(IF(MAX(D13,E13,F13,G13,H13,I13)=0,"Enter ratings",ifs(D13=MAX(D13,E13,F13,G13,H13,I13),"Power Automate",E13=MAX(D13,E13,F13,G13,H13,I13),"UiPath",F13=MAX(D13,E13,F13,G13,H13,I13),"Auto Anywhere",G13=MAX(D13,E13,F13,G13,H13,I13),"MS Copilot",H13=MAX(D13,E13,F13,G13,H13,I13),"Zapier",I13=MAX(D13,E13,F13,G13,H13,I13),"Make.com")),"Enter ratings") -> Enter ratings
A15: WEIGHTED TOTAL SCORE | B15: =SUM(B8:B13) -> 1 | C15: Max possible = 5.00 | D15: =IFERROR(SUMPRODUCT(B8:B13,D8:D13),0) -> 0 | E15: =IFERROR(SUMPRODUCT(B8:B13,E8:E13),0) -> 0 | F15: =IFERROR(SUMPRODUCT(B8:B13,F8:F13),0) -> 0 | G15: =IFERROR(SUMPRODUCT(B8:B13,G8:G13),0) -> 0 | H15: =IFERROR(SUMPRODUCT(B8:B13,H8:H13),0) -> 0 | I15: =IFERROR(SUMPRODUCT(B8:B13,I8:I13),0) -> 0 | J15: =IFERROR(IF(MAX(D15,E15,F15,G15,H15,I15)=0,"Enter ratings",ifs(D15=MAX(D15,E15,F15,G15,H15,I15),"Power Automate",E15=MAX(D15,E15,F15,G15,H15,I15),"UiPath",F15=MAX(D15,E15,F15,G15,H15,I15),"Auto Anywhere",G15=MAX(D15,E15,F15,G15,H15,I15),"MS Copilot",H15=MAX(D15,E15,F15,G15,H15,I15),"Zapier",I15=MAX(D15,E15,F15,G15,H15,I15),"Make.com")),"Enter ratings") -> Enter ratings
A17: SCORE INTERPRETATION: 4.00–5.00 = Excellent fit | 3.00–3.99 = Good fit | 2.00–2.99 = Partial fit | Below 2.00 = Poor fit

Sheet 📊 Tool Profiles
A1: 📊 AI TOOL PROFILES — Detailed Reference Guide
A2: Use this sheet to understand each platform before scoring. Data is indicative — verify with vendor for latest pricing.
A4: ATTRIBUTE | B4: Power Automate | C4: UiPath | D4: Automation Anywhere | E4: Microsoft Copilot | F4: Zapier | G4: Make.com
A5: Best For | B5: Microsoft 365 orgs wanting low-code automation | C5: Enterprise RPA with complex process automation | D5: Large enterprise — SAP, Oracle, legacy systems | E5: AI-augmented knowledge work & document creation | F5: SMEs connecting 5,000+ apps with simple flows | G5: Mid-market teams wanting visual automation
A6: Technical Skill Required | B6: Low — drag-and-drop, no coding needed | C6: Low–Medium — some scripting helpful | D6: Low–Medium — visual designer + scripting | E6: Very Low — conversational AI interface | F6: Very Low — visual flow builder | G6: Low — visual scenario builder
A7: AI / Automation Type | B7: Cloud flows, desktop RPA, AI Builder, Copilot | C7: RPA bots, AI Computer Vision, Document AI | D7: RPA bots, IQ Bot (AI document processing) | E7: Generative AI, Copilot Studio chatbots, M365 | F7: Event-based triggers, multi-step Zaps | G7: Scenario-based flows, HTTP requests, AI modules
A8: Integration Ecosystem | B8: 1,000+ connectors, native M365, SharePoint, Teams | C8: Broad: SAP, Salesforce, Oracle, ServiceNow | D8: SAP, Oracle, Mainframe, custom connectors | E8: Microsoft 365 native: Word, Excel, Outlook, Teams | F8: 5,000+ apps: Gmail, Slack, Trello, Shopify | G8: 1,000+ apps: Google Workspace, Notion, Slack
A9: Pricing (approx 2024) | B9: From USD 15/user/mo (M365 bundle discounts apply) | C9: Enterprise pricing — contact sales (USD 3K–30K+/yr) | D9: Enterprise pricing — contact sales (USD 5K+/yr) | E9: From USD 30/user/mo (M365 E3/E5 bundles) | F9: Free tier; paid from USD 20/mo (2K tasks/mo) | G9: Free tier; paid from USD 9/mo (1K ops/mo)
A10: Security & Compliance | B10: Azure AD, SOC 2, ISO 27001, GDPR, PDPA ready | C10: SOC 2 Type II, GDPR, FedRAMP (US Gov) | D10: SOC 2, FedRAMP, GDPR, HIPAA (healthcare) | E10: Microsoft Trust Center, ISO 27001, PDPA ready | F10: SOC 2 Type II, GDPR, Privacy Shield | G10: ISO 27001, GDPR, SOC 2 (Enterprise tier)
A11: Learning Resources | B11: Microsoft Learn (free), YouTube, community forums | C11: UiPath Academy (free certification courses) | D11: Automation Anywhere University (free courses) | E11: Microsoft Copilot documentation, Prompt guides | F11: Zapier University, extensive documentation | G11: Make Academy, active community forum
A12: Free Trial / Free Tier | B12: 90-day free trial; free tier with M365 | C12: Community Edition (free for individual use) | D12: Community Edition (free for individual use) | E12: Copilot free tier in M365 personal | F12: Free plan: 100 tasks/month, 5 Zaps | G12: Free plan: 1,000 ops/month, limited scenarios
A13: Recommended For This Training | B13: ★★★★★ Best for most Malaysian organisations | C13: ★★★★☆ Best for enterprise-scale automation | D13: ★★★☆☆ Best for large ERP-heavy organisations | E13: ★★★★☆ Best for knowledge worker productivity | F13: ★★★☆☆ Best for SMEs and quick app integrations | G13: ★★★☆☆ Good alternative to Zapier, more flexible

Sheet 🏆 My Recommendation
A1: 🏆 MY AI TOOL RECOMMENDATION
A2: Auto-generated from your Scoring Matrix | Print or share with management
A4: RECOMMENDED TOOL
A5: =IFERROR(IF(MAX('⚖️ Scoring Matrix'!D15:I15)=0,"Enter ratings above",'⚖️ Scoring Matrix'!J15),"Enter ratings above") -> Enter ratings above | D5: =IFERROR("Your weighted score: "&TEXT(MAX('⚖️ Scoring Matrix'!D15:I15),"0.00")&" out of 5.00","Complete the Scoring Matrix first") -> Your weighted score: 0.00 out of 5.00
A8: ALL TOOLS — SCORE SUMMARY
A9: Power Automate | B9: UiPath | C9: Auto Anywhere | D9: MS Copilot | E9: Zapier | F9: Make.com
A10: ='⚖️ Scoring Matrix'!D15 -> 0 | B10: ='⚖️ Scoring Matrix'!E15 -> 0 | C10: ='⚖️ Scoring Matrix'!F15 -> 0 | D10: ='⚖️ Scoring Matrix'!G15 -> 0 | E10: ='⚖️ Scoring Matrix'!H15 -> 0 | F10: ='⚖️ Scoring Matrix'!I15 -> 0
A12: MY SELECTION JUSTIFICATION (Fill this in)
A13: Primary reason for this choice:
A14: How it integrates with our existing systems:
A15: Expected implementation timeline:
A16: Estimated budget required:
A17: Name of person responsible for implementation:
A19: Fakhrul Syahmi | Data Consultant & Certified Trainer | mufasyahcons@gmail.com | © 2026
